[{"date": "2024-06-09T18:03:24.974000+00:00", "session_key": 9531, "interval": 0.596, "meeting_key": 1237, "gap_to_leader": 3.677, "driver_number": 2}, {"date": "2024-06-09T18:03:32.578000+00:00", "session_key": 9531, "interval": 0.352, "meeting_key": 1237, "gap_to_leader": 4.992, "driver_number": 2}, {"date": "2024-06-09T18:03:38.097000+00:00", "session_key": 9531, "interval": 0.09, "meeting_key": 1237, "gap_to_leader": 5.289, "driver_number": 2}, {"date": "2024-06-09T18:03:43.324000+00:00", "session_key": 9531, "driver_number": 2, "meeting_key": 1237, "gap_to_leader": 6.696, "interval": 0.379}, {"date": "2024-06-09T18:03:48.954000+00:00", "session_key": 9531, "driver_number": 2, "meeting_key": 1237, "gap_to_leader": 7.298, "interval": 0.378}, {"date": "2024-06-09T18:03:53.685000+00:00", "session_key": 9531, "driver_number": 2, "meeting_key": 1237, "gap_to_leader": 7.907, "interval": 0.514}, {"date": "2024-06-09T18:04:01.148000+00:00", "session_key": 9531, "driver_number": 2, "meeting_key": 1237, "gap_to_leader": 8.819, "interval": 0.569}, {"date": "2024-06-09T18:04:06.634000+00:00", "session_key": 9531, "driver_number": 2, "meeting_key": 1237, "gap_to_leader": 8.979, "interval": 0.938}, {"date": "2024-06-09T18:04:13.193000+00:00", "session_key": 9531, "driver_number": 2, "meeting_key": 1237, "gap_to_leader": 9.262, "interval": 0.675}, {"date": "2024-06-09T18:04:20.611000+00:00", "session_key": 9531, "driver_number": 2, "meeting_key": 1237, "gap_to_leader": 10.295, "interval": 0.462}, {"date": "2024-06-09T18:04:24.652000+00:00", "session_key": 9531, "driver_number": 2, "meeting_key": 1237, "gap_to_leader": 10.595, "interval": 0.529}, {"date": "2024-06-09T18:04:28.224000+00:00", "session_key": 9531, "driver_number": 2, "meeting_key": 1237, "gap_to_leader": 10.736, "interval": 0.539}, {"date": "2024-06-09T18:04:37.738000+00:00", "session_key": 9531, "interval": 0.56, "meeting_key": 1237, "gap_to_leader": 11.648, "driver_number": 2}, {"date": "2024-06-09T18:04:44.230000+00:00", "session_key": 9531, "interval": 0.189, "meeting_key": 1237, "gap_to_leader": 11.895, "driver_number": 2}, {"date": "2024-06-09T18:04:47.376000+00:00", "session_key": 9531, "interval": 0.094, "meeting_key": 1237, "gap_to_leader": 11.868, "driver_number": 2}, {"date": "2024-06-09T18:04:52.668000+00:00", "session_key": 9531, "interval": 0.145, "meeting_key": 1237, "gap_to_leader": 12.118, "driver_number": 2}, {"date": "2024-06-09T18:04:58.901000+00:00", "session_key": 9531, "interval": 0.478, "meeting_key": 1237, "gap_to_leader": 13.104, "driver_number": 2}, {"date": "2024-06-09T18:05:03.275000+00:00", "session_key": 9531, "interval": 0.322, "meeting_key": 1237, "gap_to_leader": 13.412, "driver_number": 2}, {"date": "2024-06-09T18:05:09.540000+00:00", "session_key": 9531, "interval": 0.022, "meeting_key": 1237, "gap_to_leader": 13.962, "driver_number": 2}, {"date": "2024-06-09T18:05:14.058000+00:00", "session_key": 9531, "interval": null, "meeting_key": 1237, "gap_to_leader": 14.379, "driver_number": 2}, {"date": "2024-06-09T18:05:20.592000+00:00", "session_key": 9531, "interval": null, "meeting_key": 1237, "gap_to_leader": 14.814, "driver_number": 2}, {"date": "2024-06-09T18:05:25.964000+00:00", "session_key": 9531, "driver_number": 2, "meeting_key": 1237, "gap_to_leader": 14.996, "interval": 1.411}, {"date": "2024-06-09T18:05:30.022000+00:00", "session_key": 9531, "driver_number": 2, "meeting_key": 1237, "gap_to_leader": 15.348, "interval": 1.248}, {"date": "2024-06-09T18:05:35.154000+00:00", "session_key": 9531, "driver_number": 2, "meeting_key": 1237, "gap_to_leader": 15.664, "interval": 1.309}, {"date": "2024-06-09T18:05:39.057000+00:00", "session_key": 9531, "driver_number": 2, "meeting_key": 1237, "gap_to_leader": 15.77, "interval": 1.151}, {"date": "2024-06-09T18:05:46.229000+00:00", "session_key": 9531, "driver_number": 2, "meeting_key": 1237, "gap_to_leader": 16.292, "interval": 0.997}, {"date": "2024-06-09T18:05:51.304000+00:00", "session_key": 9531, "driver_number": 2, "meeting_key": 1237, "gap_to_leader": 16.666, "interval": 0.911}, {"date": "2024-06-09T18:05:57.686000+00:00", "session_key": 9531, "driver_number": 2, "meeting_key": 1237, "gap_to_leader": 16.988, "interval": 0.831}, {"date": "2024-06-09T18:06:04.301000+00:00", "session_key": 9531, "driver_number": 2, "meeting_key": 1237, "gap_to_leader": 17.457, "interval": 0.73}, {"date": "2024-06-09T18:06:08.362000+00:00", "session_key": 9531, "driver_number": 2, "meeting_key": 1237, "gap_to_leader": 17.713, "interval": 0.782}, {"date": "2024-06-09T18:06:11.804000+00:00", "session_key": 9531, "driver_number": 2, "meeting_key": 1237, "gap_to_leader": 17.767, "interval": 0.755}, {"date": "2024-06-09T18:06:20.744000+00:00", "session_key": 9531, "driver_number": 2, "meeting_key": 1237, "gap_to_leader": 18.371, "interval": 0.358}, {"date": "2024-06-09T18:06:27.199000+00:00", "session_key": 9531, "driver_number": 2, "meeting_key": 1237, "gap_to_leader": 18.833, "interval": 0.475}, {"date": "2024-06-09T18:06:30.345000+00:00", "session_key": 9531, "driver_number": 2, "meeting_key": 1237, "gap_to_leader": 18.836, "interval": 0.459}, {"date": "2024-06-09T18:06:35.191000+00:00", "session_key": 9531, "driver_number": 2, "meeting_key": 1237, "gap_to_leader": 18.647, "interval": 0.359}, {"date": "2024-06-09T18:06:41.138000+00:00", "session_key": 9531, "driver_number": 2, "meeting_key": 1237, "gap_to_leader": 19.709, "interval": 0.435}, {"date": "2024-06-09T18:06:45.240000+00:00", "session_key": 9531, "driver_number": 2, "meeting_key": 1237, "gap_to_leader": 19.9, "interval": 0.46}, {"date": "2024-06-09T18:06:51.042000+00:00", "session_key": 9531, "driver_number": 2, "meeting_key": 1237, "gap_to_leader": 18.953, "interval": 0.535}, {"date": "2024-06-09T18:06:55.652000+00:00", "session_key": 9531, "driver_number": 2, "meeting_key": 1237, "gap_to_leader": 19.52, "interval": 0.6}, {"date": "2024-06-09T18:07:02.012000+00:00", "session_key": 9531, "driver_number": 2, "meeting_key": 1237, "gap_to_leader": 19.905, "interval": 0.816}, {"date": "2024-06-09T18:07:07.468000+00:00", "session_key": 9531, "driver_number": 2, "meeting_key": 1237, "gap_to_leader": 20.157, "interval": 0.799}, {"date": "2024-06-09T18:07:11.592000+00:00", "session_key": 9531, "driver_number": 2, "meeting_key": 1237, "gap_to_leader": 20.329, "interval": 0.824}, {"date": "2024-06-09T18:07:16.694000+00:00", "session_key": 9531, "driver_number": 2, "meeting_key": 1237, "gap_to_leader": 20.571, "interval": 0.889}, {"date": "2024-06-09T18:07:20.846000+00:00", "session_key": 9531, "driver_number": 2, "meeting_key": 1237, "gap_to_leader": 21.02, "interval": 1.033}, {"date": "2024-06-09T18:07:27.786000+00:00", "session_key": 9531, "driver_number": 2, "meeting_key": 1237, "gap_to_leader": 21.328, "interval": 1.015}, {"date": "2024-06-09T18:07:33.044000+00:00", "session_key": 9531, "driver_number": 2, "meeting_key": 1237, "gap_to_leader": 21.147, "interval": null}, {"date": "2024-06-09T18:07:39.346000+00:00", "session_key": 9531, "interval": 1.021, "meeting_key": 1237, "gap_to_leader": 21.398, "driver_number": 2}, {"date": "2024-06-09T18:07:45.785000+00:00", "session_key": 9531, "interval": 0.886, "meeting_key": 1237, "gap_to_leader": 21.608, "driver_number": 2}, {"date": "2024-06-09T18:07:49.727000+00:00", "session_key": 9531, "interval": 0.965, "meeting_key": 1237, "gap_to_leader": 21.793, "driver_number": 2}, {"date": "2024-06-09T18:07:53.149000+00:00", "session_key": 9531, "interval": 0.948, "meeting_key": 1237, "gap_to_leader": 21.823, "driver_number": 2}, {"date": "2024-06-09T18:08:01.731000+00:00", "session_key": 9531, "interval": 0.746, "meeting_key": 1237, "gap_to_leader": 22.102, "driver_number": 2}, {"date": "2024-06-09T18:08:08.255000+00:00", "session_key": 9531, "interval": null, "meeting_key": 1237, "gap_to_leader": 22.699, "driver_number": 2}, {"date": "2024-06-09T18:08:11.402000+00:00", "session_key": 9531, "interval": 0.771, "meeting_key": 1237, "gap_to_leader": 22.721, "driver_number": 2}, {"date": "2024-06-09T18:08:16.269000+00:00", "session_key": 9531, "interval": 0.749, "meeting_key": 1237, "gap_to_leader": 22.578, "driver_number": 2}, {"date": "2024-06-09T18:08:21.509000+00:00", "session_key": 9531, "interval": 0.534, "meeting_key": 1237, "gap_to_leader": 22.628, "driver_number": 2}, {"date": "2024-06-09T18:08:25.685000+00:00", "session_key": 9531, "interval": 0.794, "meeting_key": 1237, "gap_to_leader": 22.699, "driver_number": 2}, {"date": "2024-06-09T18:08:32.831000+00:00", "session_key": 9531, "interval": 0.262, "meeting_key": 1237, "gap_to_leader": 24.306, "driver_number": 2}, {"date": "2024-06-09T18:08:37.233000+00:00", "session_key": 9531, "interval": 0.592, "meeting_key": 1237, "gap_to_leader": 24.882, "driver_number": 2}, {"date": "2024-06-09T18:08:43.561000+00:00", "session_key": 9531, "interval": 0.517, "meeting_key": 1237, "gap_to_leader": 25.092, "driver_number": 2}, {"date": "2024-06-09T18:08:49.225000+00:00", "session_key": 9531, "interval": 0.632, "meeting_key": 1237, "gap_to_leader": 25.622, "driver_number": 2}, {"date": "2024-06-09T18:08:53.420000+00:00", "session_key": 9531, "interval": 0.919, "meeting_key": 1237, "gap_to_leader": 26.063, "driver_number": 2}, {"date": "2024-06-09T18:08:58.351000+00:00", "session_key": 9531, "interval": 1.12, "meeting_key": 1237, "gap_to_leader": 26.142, "driver_number": 2}, {"date": "2024-06-09T18:09:02.286000+00:00", "session_key": 9531, "interval": 1.136, "meeting_key": 1237, "gap_to_leader": 26.387, "driver_number": 2}, {"date": "2024-06-09T18:09:08.872000+00:00", "session_key": 9531, "interval": 1.21, "meeting_key": 1237, "gap_to_leader": 26.415, "driver_number": 2}, {"date": "2024-06-09T18:09:14.072000+00:00", "session_key": 9531, "interval": 1.338, "meeting_key": 1237, "gap_to_leader": 26.825, "driver_number": 2}, {"date": "2024-06-09T18:09:20.205000+00:00", "session_key": 9531, "interval": 1.206, "meeting_key": 1237, "gap_to_leader": 27.048, "driver_number": 2}, {"date": "2024-06-09T18:09:26.693000+00:00", "session_key": 9531, "interval": 1.436, "meeting_key": 1237, "gap_to_leader": 27.433, "driver_number": 2}, {"date": "2024-06-09T18:09:30.606000+00:00", "session_key": 9531, "interval": 1.32, "meeting_key": 1237, "gap_to_leader": 27.682, "driver_number": 2}, {"date": "2024-06-09T18:09:34.034000+00:00", "session_key": 9531, "interval": 1.285, "meeting_key": 1237, "gap_to_leader": 27.732, "driver_number": 2}, {"date": "2024-06-09T18:09:42.400000+00:00", "session_key": 9531, "interval": 1.195, "meeting_key": 1237, "gap_to_leader": 27.564, "driver_number": 2}, {"date": "2024-06-09T18:09:48.561000+00:00", "session_key": 9531, "interval": 1.256, "meeting_key": 1237, "gap_to_leader": 28.096, "driver_number": 2}, {"date": "2024-06-09T18:09:51.664000+00:00", "session_key": 9531, "driver_number": 2, "meeting_key": 1237, "gap_to_leader": 28.1, "interval": 1.239}, {"date": "2024-06-09T18:09:56.493000+00:00", "session_key": 9531, "driver_number": 2, "meeting_key": 1237, "gap_to_leader": 27.961, "interval": 1.149}, {"date": "2024-06-09T18:10:01.823000+00:00", "session_key": 9531, "driver_number": 2, "meeting_key": 1237, "gap_to_leader": 28.1, "interval": 1.176}, {"date": "2024-06-09T18:10:05.726000+00:00", "session_key": 9531, "driver_number": 2, "meeting_key": 1237, "gap_to_leader": 28.122, "interval": 1.23}, {"date": "2024-06-09T18:10:11.360000+00:00", "session_key": 9531, "driver_number": 2, "meeting_key": 1237, "gap_to_leader": 28.242, "interval": 1.152}, {"date": "2024-06-09T18:10:15.230000+00:00", "session_key": 9531, "driver_number": 2, "meeting_key": 1237, "gap_to_leader": 28.369, "interval": 1.208}, {"date": "2024-06-09T18:10:27.450000+00:00", "session_key": 9531, "driver_number": 2, "meeting_key": 1237, "gap_to_leader": 29.323, "interval": null}, {"date": "2024-06-09T18:10:31.758000+00:00", "session_key": 9531, "driver_number": 2, "meeting_key": 1237, "gap_to_leader": 29.978, "interval": 1.471}, {"date": "2024-06-09T18:10:36.772000+00:00", "session_key": 9531, "driver_number": 2, "meeting_key": 1237, "gap_to_leader": 29.987, "interval": 1.72}, {"date": "2024-06-09T18:10:40.797000+00:00", "session_key": 9531, "driver_number": 2, "meeting_key": 1237, "gap_to_leader": 30.214, "interval": 1.813}, {"date": "2024-06-09T18:10:47.347000+00:00", "session_key": 9531, "interval": 1.822, "meeting_key": 1237, "gap_to_leader": 30.285, "driver_number": 2}, {"date": "2024-06-09T18:10:52.284000+00:00", "session_key": 9531, "interval": 1.732, "meeting_key": 1237, "gap_to_leader": 30.625, "driver_number": 2}, {"date": "2024-06-09T18:10:58.452000+00:00", "session_key": 9531, "interval": 1.679, "meeting_key": 1237, "gap_to_leader": 30.834, "driver_number": 2}, {"date": "2024-06-09T18:11:04.820000+00:00", "session_key": 9531, "interval": 1.849, "meeting_key": 1237, "gap_to_leader": 31.06, "driver_number": 2}, {"date": "2024-06-09T18:11:08.534000+00:00", "session_key": 9531, "interval": 1.645, "meeting_key": 1237, "gap_to_leader": 31.098, "driver_number": 2}, {"date": "2024-06-09T18:11:11.866000+00:00", "session_key": 9531, "interval": 1.571, "meeting_key": 1237, "gap_to_leader": 31.107, "driver_number": 2}, {"date": "2024-06-09T18:11:21.179000+00:00", "session_key": 9531, "interval": 2.406, "meeting_key": 1237, "gap_to_leader": 32.231, "driver_number": 2}, {"date": "2024-06-09T18:11:27.029000+00:00", "session_key": 9531, "interval": 2.006, "meeting_key": 1237, "gap_to_leader": 32.279, "driver_number": 2}, {"date": "2024-06-09T18:11:30.124000+00:00", "session_key": 9531, "interval": 1.978, "meeting_key": 1237, "gap_to_leader": 32.307, "driver_number": 2}, {"date": "2024-06-09T18:11:35.007000+00:00", "session_key": 9531, "interval": 1.935, "meeting_key": 1237, "gap_to_leader": 32.244, "driver_number": 2}, {"date": "2024-06-09T18:11:40.378000+00:00", "session_key": 9531, "interval": 2.138, "meeting_key": 1237, "gap_to_leader": 32.477, "driver_number": 2}, {"date": "2024-06-09T18:11:44.164000+00:00", "session_key": 9531, "interval": 2.215, "meeting_key": 1237, "gap_to_leader": 32.403, "driver_number": 2}, {"date": "2024-06-09T18:11:49.702000+00:00", "session_key": 9531, "interval": 2.133, "meeting_key": 1237, "gap_to_leader": 32.508, "driver_number": 2}, {"date": "2024-06-09T18:11:53.775000+00:00", "session_key": 9531, "interval": 2.397, "meeting_key": 1237, "gap_to_leader": 32.942, "driver_number": 2}, {"date": "2024-06-09T18:12:00.067000+00:00", "session_key": 9531, "interval": 2.217, "meeting_key": 1237, "gap_to_leader": 33.151, "driver_number": 2}, {"date": "2024-06-09T18:12:05.427000+00:00", "session_key": 9531, "interval": 2.339, "meeting_key": 1237, "gap_to_leader": 33.466, "driver_number": 2}, {"date": "2024-06-09T18:12:09.100000+00:00", "session_key": 9531, "interval": 2.394, "meeting_key": 1237, "gap_to_leader": 33.54, "driver_number": 2}, {"date": "2024-06-09T18:12:13.986000+00:00", "session_key": 9531, "interval": 2.403, "meeting_key": 1237, "gap_to_leader": 33.504, "driver_number": 2}, {"date": "2024-06-09T18:12:17.726000+00:00", "session_key": 9531, "interval": 2.451, "meeting_key": 1237, "gap_to_leader": 33.722, "driver_number": 2}, {"date": "2024-06-09T18:12:45.594000+00:00", "session_key": 9531, "interval": 11.594, "meeting_key": 1237, "gap_to_leader": 55.128, "driver_number": 2}, {"date": "2024-06-09T18:12:50.985000+00:00", "session_key": 9531, "interval": 12.046, "meeting_key": 1237, "gap_to_leader": 56.002, "driver_number": 2}, {"date": "2024-06-09T18:12:57.401000+00:00", "session_key": 9531, "interval": 12.172, "meeting_key": 1237, "gap_to_leader": 56.483, "driver_number": 2}, {"date": "2024-06-09T18:13:03.749000+00:00", "session_key": 9531, "interval": 12.3, "meeting_key": 1237, "gap_to_leader": 56.941, "driver_number": 2}, {"date": "2024-06-09T18:13:07.548000+00:00", "session_key": 9531, "interval": 12.304, "meeting_key": 1237, "gap_to_leader": 57.17, "driver_number": 2}, {"date": "2024-06-09T18:13:10.931000+00:00", "session_key": 9531, "interval": 12.323, "meeting_key": 1237, "gap_to_leader": 57.245, "driver_number": 2}, {"date": "2024-06-09T18:13:19.520000+00:00", "session_key": 9531, "interval": 12.253, "meeting_key": 1237, "gap_to_leader": 57.311, "driver_number": 2}, {"date": "2024-06-09T18:13:25.535000+00:00", "session_key": 9531, "interval": 12.192, "meeting_key": 1237, "gap_to_leader": 57.753, "driver_number": 2}, {"date": "2024-06-09T18:13:28.724000+00:00", "session_key": 9531, "interval": 12.179, "meeting_key": 1237, "gap_to_leader": 57.775, "driver_number": 2}, {"date": "2024-06-09T18:13:33.518000+00:00", "session_key": 9531, "interval": 12.168, "meeting_key": 1237, "gap_to_leader": 57.736, "driver_number": 2}, {"date": "2024-06-09T18:13:38.774000+00:00", "session_key": 9531, "interval": 11.895, "meeting_key": 1237, "gap_to_leader": 57.794, "driver_number": 2}, {"date": "2024-06-09T18:13:42.600000+00:00", "session_key": 9531, "interval": 11.913, "meeting_key": 1237, "gap_to_leader": 57.862, "driver_number": 2}, {"date": "2024-06-09T18:13:48.036000+00:00", "session_key": 9531, "interval": 11.907, "meeting_key": 1237, "gap_to_leader": 57.935, "driver_number": 2}, {"date": "2024-06-09T18:13:52.133000+00:00", "session_key": 9531, "interval": 11.957, "meeting_key": 1237, "gap_to_leader": 58.402, "driver_number": 2}, {"date": "2024-06-09T18:13:58.255000+00:00", "session_key": 9531, "interval": 11.778, "meeting_key": 1237, "gap_to_leader": 58.422, "driver_number": 2}, {"date": "2024-06-09T18:14:03.374000+00:00", "session_key": 9531, "driver_number": 2, "meeting_key": 1237, "gap_to_leader": 58.661, "interval": 11.565}, {"date": "2024-06-09T18:14:07.063000+00:00", "session_key": 9531, "driver_number": 2, "meeting_key": 1237, "gap_to_leader": 58.951, "interval": 11.295}, {"date": "2024-06-09T18:14:11.725000+00:00", "session_key": 9531, "driver_number": 2, "meeting_key": 1237, "gap_to_leader": 59.01, "interval": 11.248}, {"date": "2024-06-09T18:14:15.468000+00:00", "session_key": 9531, "driver_number": 2, "meeting_key": 1237, "gap_to_leader": 59.259, "interval": 11.281}, {"date": "2024-06-09T18:14:21.984000+00:00", "session_key": 9531, "driver_number": 2, "meeting_key": 1237, "gap_to_leader": 59.418, "interval": 11.393}, {"date": "2024-06-09T18:14:26.517000+00:00", "session_key": 9531, "driver_number": 2, "meeting_key": 1237, "gap_to_leader": 59.552, "interval": 11.309}, {"date": "2024-06-09T18:14:32.456000+00:00", "session_key": 9531, "driver_number": 2, "meeting_key": 1237, "gap_to_leader": 59.651, "interval": 11.266}, {"date": "2024-06-09T18:14:38.617000+00:00", "session_key": 9531, "driver_number": 2, "meeting_key": 1237, "gap_to_leader": 59.993, "interval": 11.297}, {"date": "2024-06-09T18:14:42.370000+00:00", "session_key": 9531, "interval": 11.351, "meeting_key": 1237, "gap_to_leader": 60.273, "driver_number": 2}, {"date": "2024-06-09T18:14:45.762000+00:00", "session_key": 9531, "interval": 11.408, "meeting_key": 1237, "gap_to_leader": 60.376, "driver_number": 2}, {"date": "2024-06-09T18:14:54.062000+00:00", "session_key": 9531, "interval": 11.213, "meeting_key": 1237, "gap_to_leader": 60.515, "driver_number": 2}, {"date": "2024-06-09T18:14:59.842000+00:00", "session_key": 9531, "interval": 11.031, "meeting_key": 1237, "gap_to_leader": 60.674, "driver_number": 2}, {"date": "2024-06-09T18:15:02.907000+00:00", "session_key": 9531, "interval": 11.013, "meeting_key": 1237, "gap_to_leader": 60.697, "driver_number": 2}, {"date": "2024-06-09T18:15:07.832000+00:00", "session_key": 9531, "interval": 10.997, "meeting_key": 1237, "gap_to_leader": 60.654, "driver_number": 2}, {"date": "2024-06-09T18:15:12.900000+00:00", "session_key": 9531, "interval": 10.708, "meeting_key": 1237, "gap_to_leader": 60.723, "driver_number": 2}, {"date": "2024-06-09T18:15:16.634000+00:00", "session_key": 9531, "interval": 10.666, "meeting_key": 1237, "gap_to_leader": 60.841, "driver_number": 2}, {"date": "2024-06-09T18:15:22.074000+00:00", "session_key": 9531, "interval": 10.62, "meeting_key": 1237, "gap_to_leader": 60.992, "driver_number": 2}, {"date": "2024-06-09T18:15:26.126000+00:00", "session_key": 9531, "driver_number": 2, "meeting_key": 1237, "gap_to_leader": 61.36, "interval": 10.7}, {"date": "2024-06-09T18:15:32.217000+00:00", "session_key": 9531, "driver_number": 2, "meeting_key": 1237, "gap_to_leader": 61.555, "interval": 10.8}, {"date": "2024-06-09T18:15:37.230000+00:00", "session_key": 9531, "driver_number": 2, "meeting_key": 1237, "gap_to_leader": 61.378, "interval": 10.679}, {"date": "2024-06-09T18:15:40.655000+00:00", "session_key": 9531, "driver_number": 2, "meeting_key": 1237, "gap_to_leader": 61.322, "interval": 10.512}, {"date": "2024-06-09T18:15:45.890000+00:00", "session_key": 9531, "interval": 10.923, "meeting_key": 1237, "gap_to_leader": 61.742, "driver_number": 2}, {"date": "2024-06-09T18:15:49.924000+00:00", "session_key": 9531, "interval": 11.249, "meeting_key": 1237, "gap_to_leader": 62.233, "driver_number": 2}, {"date": "2024-06-09T18:15:56.298000+00:00", "session_key": 9531, "interval": 11.429, "meeting_key": 1237, "gap_to_leader": 62.369, "driver_number": 2}, {"date": "2024-06-09T18:16:01.085000+00:00", "session_key": 9531, "interval": 11.494, "meeting_key": 1237, "gap_to_leader": 62.606, "driver_number": 2}, {"date": "2024-06-09T18:16:06.993000+00:00", "session_key": 9531, "interval": 11.527, "meeting_key": 1237, "gap_to_leader": 62.675, "driver_number": 2}, {"date": "2024-06-09T18:16:13.284000+00:00", "session_key": 9531, "interval": 11.585, "meeting_key": 1237, "gap_to_leader": 63.028, "driver_number": 2}, {"date": "2024-06-09T18:16:16.916000+00:00", "session_key": 9531, "interval": 11.532, "meeting_key": 1237, "gap_to_leader": 63.147, "driver_number": 2}, {"date": "2024-06-09T18:16:20.195000+00:00", "session_key": 9531, "interval": 11.542, "meeting_key": 1237, "gap_to_leader": 63.19, "driver_number": 2}, {"date": "2024-06-09T18:16:28.351000+00:00", "session_key": 9531, "interval": 11.338, "meeting_key": 1237, "gap_to_leader": 63.399, "driver_number": 2}, {"date": "2024-06-09T18:16:34.169000+00:00", "session_key": 9531, "interval": 11.265, "meeting_key": 1237, "gap_to_leader": 63.556, "driver_number": 2}, {"date": "2024-06-09T18:16:37.226000+00:00", "session_key": 9531, "interval": 11.249, "meeting_key": 1237, "gap_to_leader": 63.557, "driver_number": 2}, {"date": "2024-06-09T18:16:42.104000+00:00", "session_key": 9531, "interval": 11.222, "meeting_key": 1237, "gap_to_leader": 63.464, "driver_number": 2}, {"date": "2024-06-09T18:16:47.260000+00:00", "session_key": 9531, "interval": 11.144, "meeting_key": 1237, "gap_to_leader": 63.621, "driver_number": 2}, {"date": "2024-06-09T18:16:50.863000+00:00", "session_key": 9531, "interval": 10.986, "meeting_key": 1237, "gap_to_leader": 63.631, "driver_number": 2}, {"date": "2024-06-09T18:16:56.229000+00:00", "session_key": 9531, "interval": 10.892, "meeting_key": 1237, "gap_to_leader": 63.686, "driver_number": 2}, {"date": "2024-06-09T18:17:00.292000+00:00", "session_key": 9531, "interval": 10.982, "meeting_key": 1237, "gap_to_leader": 63.961, "driver_number": 2}, {"date": "2024-06-09T18:17:06.128000+00:00", "session_key": 9531, "interval": 10.887, "meeting_key": 1237, "gap_to_leader": 63.882, "driver_number": 2}, {"date": "2024-06-09T18:17:11.358000+00:00", "session_key": 9531, "interval": 11.071, "meeting_key": 1237, "gap_to_leader": 64.179, "driver_number": 2}, {"date": "2024-06-09T18:17:14.975000+00:00", "session_key": 9531, "interval": 11.095, "meeting_key": 1237, "gap_to_leader": 64.295, "driver_number": 2}, {"date": "2024-06-09T18:17:19.568000+00:00", "session_key": 9531, "interval": 10.96, "meeting_key": 1237, "gap_to_leader": 64.194, "driver_number": 2}, {"date": "2024-06-09T18:17:23.349000+00:00", "session_key": 9531, "interval": 10.963, "meeting_key": 1237, "gap_to_leader": 64.304, "driver_number": 2}, {"date": "2024-06-09T18:17:29.430000+00:00", "session_key": 9531, "interval": 11.195, "meeting_key": 1237, "gap_to_leader": 64.243, "driver_number": 2}, {"date": "2024-06-09T18:17:34.059000+00:00", "session_key": 9531, "interval": 10.931, "meeting_key": 1237, "gap_to_leader": 64.349, "driver_number": 2}, {"date": "2024-06-09T18:17:39.834000+00:00", "session_key": 9531, "interval": 10.858, "meeting_key": 1237, "gap_to_leader": 64.429, "driver_number": 2}, {"date": "2024-06-09T18:17:45.745000+00:00", "session_key": 9531, "interval": 10.587, "meeting_key": 1237, "gap_to_leader": 64.69200000000001, "driver_number": 2}, {"date": "2024-06-09T18:17:49.195000+00:00", "session_key": 9531, "interval": 10.43, "meeting_key": 1237, "gap_to_leader": 64.771, "driver_number": 2}, {"date": "2024-06-09T18:17:52.508000+00:00", "session_key": 9531, "interval": 10.414, "meeting_key": 1237, "gap_to_leader": 64.805, "driver_number": 2}, {"date": "2024-06-09T18:18:00.561000+00:00", "session_key": 9531, "interval": 10.282, "meeting_key": 1237, "gap_to_leader": 65.026, "driver_number": 2}, {"date": "2024-06-09T18:18:06.308000+00:00", "session_key": 9531, "driver_number": 2, "meeting_key": 1237, "gap_to_leader": 65.156, "interval": 10.22}, {"date": "2024-06-09T18:18:09.355000+00:00", "session_key": 9531, "driver_number": 2, "meeting_key": 1237, "gap_to_leader": 65.168, "interval": 10.204}, {"date": "2024-06-09T18:18:14.246000+00:00", "session_key": 9531, "driver_number": 2, "meeting_key": 1237, "gap_to_leader": 65.117, "interval": 10.16}, {"date": "2024-06-09T18:18:19.296000+00:00", "session_key": 9531, "driver_number": 2, "meeting_key": 1237, "gap_to_leader": 65.248, "interval": 10.014}, {"date": "2024-06-09T18:18:22.854000+00:00", "session_key": 9531, "driver_number": 2, "meeting_key": 1237, "gap_to_leader": 65.228, "interval": 9.894}, {"date": "2024-06-09T18:18:28.209000+00:00", "session_key": 9531, "driver_number": 2, "meeting_key": 1237, "gap_to_leader": 65.252, "interval": 9.795}, {"date": "2024-06-09T18:18:31.980000+00:00", "session_key": 9531, "driver_number": 2, "meeting_key": 1237, "gap_to_leader": 65.465, "interval": 9.785}, {"date": "2024-06-09T18:18:37.934000+00:00", "session_key": 9531, "driver_number": 2, "meeting_key": 1237, "gap_to_leader": 65.409, "interval": 9.739}, {"date": "2024-06-09T18:18:42.866000+00:00", "session_key": 9531, "driver_number": 2, "meeting_key": 1237, "gap_to_leader": 65.43, "interval": 9.801}, {"date": "2024-06-09T18:18:46.402000+00:00", "session_key": 9531, "driver_number": 2, "meeting_key": 1237, "gap_to_leader": 65.53, "interval": 9.836}, {"date": "2024-06-09T18:18:51.069000+00:00", "session_key": 9531, "driver_number": 2, "meeting_key": 1237, "gap_to_leader": 65.678, "interval": 9.877}, {"date": "2024-06-09T18:18:54.752000+00:00", "session_key": 9531, "driver_number": 2, "meeting_key": 1237, "gap_to_leader": 65.928, "interval": 9.944}, {"date": "2024-06-09T18:19:00.927000+00:00", "session_key": 9531, "driver_number": 2, "meeting_key": 1237, "gap_to_leader": 65.944, "interval": 9.607}, {"date": "2024-06-09T18:19:05.315000+00:00", "session_key": 9531, "driver_number": 2, "meeting_key": 1237, "gap_to_leader": 65.992, "interval": 9.122}, {"date": "2024-06-09T18:19:11.232000+00:00", "session_key": 9531, "driver_number": 2, "meeting_key": 1237, "gap_to_leader": 66.049, "interval": 9.032}, {"date": "2024-06-09T18:19:17.081000+00:00", "session_key": 9531, "driver_number": 2, "meeting_key": 1237, "gap_to_leader": 66.147, "interval": 8.749}, {"date": "2024-06-09T18:19:20.496000+00:00", "session_key": 9531, "driver_number": 2, "meeting_key": 1237, "gap_to_leader": 66.206, "interval": 8.625}, {"date": "2024-06-09T18:19:23.759000+00:00", "session_key": 9531, "driver_number": 2, "meeting_key": 1237, "gap_to_leader": 66.219, "interval": 8.599}, {"date": "2024-06-09T18:19:31.855000+00:00", "session_key": 9531, "driver_number": 2, "meeting_key": 1237, "gap_to_leader": 66.304, "interval": 8.35}, {"date": "2024-06-09T18:19:37.506000+00:00", "session_key": 9531, "driver_number": 2, "meeting_key": 1237, "gap_to_leader": 66.436, "interval": 8.354}, {"date": "2024-06-09T18:19:40.559000+00:00", "session_key": 9531, "driver_number": 2, "meeting_key": 1237, "gap_to_leader": 66.431, "interval": 8.334}, {"date": "2024-06-09T18:19:45.409000+00:00", "session_key": 9531, "interval": 8.296, "meeting_key": 1237, "gap_to_leader": 66.35, "driver_number": 2}, {"date": "2024-06-09T18:19:50.368000+00:00", "session_key": 9531, "interval": 8.156, "meeting_key": 1237, "gap_to_leader": 66.477, "driver_number": 2}, {"date": "2024-06-09T18:19:54.083000+00:00", "session_key": 9531, "interval": 7.995, "meeting_key": 1237, "gap_to_leader": 66.483, "driver_number": 2}, {"date": "2024-06-09T18:19:59.237000+00:00", "session_key": 9531, "interval": 7.949, "meeting_key": 1237, "gap_to_leader": 66.522, "driver_number": 2}, {"date": "2024-06-09T18:20:02.961000+00:00", "session_key": 9531, "interval": 8.013, "meeting_key": 1237, "gap_to_leader": 66.702, "driver_number": 2}, {"date": "2024-06-09T18:20:08.945000+00:00", "session_key": 9531, "interval": 8.02, "meeting_key": 1237, "gap_to_leader": 66.693, "driver_number": 2}, {"date": "2024-06-09T18:20:13.794000+00:00", "session_key": 9531, "interval": 7.908, "meeting_key": 1237, "gap_to_leader": 66.691, "driver_number": 2}, {"date": "2024-06-09T18:20:17.218000+00:00", "session_key": 9531, "interval": 7.722, "meeting_key": 1237, "gap_to_leader": 66.699, "driver_number": 2}, {"date": "2024-06-09T18:20:21.748000+00:00", "session_key": 9531, "interval": 7.68, "meeting_key": 1237, "gap_to_leader": 66.731, "driver_number": 2}, {"date": "2024-06-09T18:20:25.380000+00:00", "session_key": 9531, "interval": 7.743, "meeting_key": 1237, "gap_to_leader": 66.834, "driver_number": 2}, {"date": "2024-06-09T18:20:31.422000+00:00", "session_key": 9531, "interval": 7.71, "meeting_key": 1237, "gap_to_leader": 66.654, "driver_number": 2}, {"date": "2024-06-09T18:20:35.914000+00:00", "session_key": 9531, "interval": 7.389, "meeting_key": 1237, "gap_to_leader": 66.732, "driver_number": 2}, {"date": "2024-06-09T18:20:41.747000+00:00", "session_key": 9531, "driver_number": 2, "meeting_key": 1237, "gap_to_leader": 66.794, "interval": 7.266}, {"date": "2024-06-09T18:20:47.579000+00:00", "session_key": 9531, "driver_number": 2, "meeting_key": 1237, "gap_to_leader": 66.73, "interval": 6.942}, {"date": "2024-06-09T18:20:51.008000+00:00", "session_key": 9531, "driver_number": 2, "meeting_key": 1237, "gap_to_leader": 66.775, "interval": 6.758}, {"date": "2024-06-09T18:20:54.253000+00:00", "session_key": 9531, "driver_number": 2, "meeting_key": 1237, "gap_to_leader": 66.799, "interval": 6.724}, {"date": "2024-06-09T18:21:02.274000+00:00", "session_key": 9531, "interval": 6.824, "meeting_key": 1237, "gap_to_leader": 67.006, "driver_number": 2}, {"date": "2024-06-09T18:21:07.853000+00:00", "session_key": 9531, "interval": 6.683, "meeting_key": 1237, "gap_to_leader": 67.06, "driver_number": 2}, {"date": "2024-06-09T18:21:10.934000+00:00", "session_key": 9531, "interval": 6.668, "meeting_key": 1237, "gap_to_leader": 67.064, "driver_number": 2}, {"date": "2024-06-09T18:21:15.747000+00:00", "session_key": 9531, "interval": 6.614, "meeting_key": 1237, "gap_to_leader": 66.999, "driver_number": 2}, {"date": "2024-06-09T18:21:20.504000+00:00", "session_key": 9531, "interval": 6.257, "meeting_key": 1237, "gap_to_leader": 66.925, "driver_number": 2}, {"date": "2024-06-09T18:21:24.067000+00:00", "session_key": 9531, "interval": 6.107, "meeting_key": 1237, "gap_to_leader": 66.855, "driver_number": 2}, {"date": "2024-06-09T18:21:29.326000+00:00", "session_key": 9531, "interval": 6.033, "meeting_key": 1237, "gap_to_leader": 66.856, "driver_number": 2}, {"date": "2024-06-09T18:21:33.130000+00:00", "session_key": 9531, "interval": 6.25, "meeting_key": 1237, "gap_to_leader": 67.0, "driver_number": 2}, {"date": "2024-06-09T18:21:38.870000+00:00", "session_key": 9531, "interval": 6.17, "meeting_key": 1237, "gap_to_leader": 66.824, "driver_number": 2}, {"date": "2024-06-09T18:21:43.808000+00:00", "session_key": 9531, "driver_number": 2, "meeting_key": 1237, "gap_to_leader": 66.764, "interval": 5.989}, {"date": "2024-06-09T18:21:47.121000+00:00", "session_key": 9531, "driver_number": 2, "meeting_key": 1237, "gap_to_leader": 66.689, "interval": 5.926}, {"date": "2024-06-09T18:21:51.591000+00:00", "session_key": 9531, "driver_number": 2, "meeting_key": 1237, "gap_to_leader": 66.68, "interval": 5.76}, {"date": "2024-06-09T18:21:55.261000+00:00", "session_key": 9531, "driver_number": 2, "meeting_key": 1237, "gap_to_leader": 66.848, "interval": 5.858}, {"date": "2024-06-09T18:22:01.268000+00:00", "session_key": 9531, "driver_number": 2, "meeting_key": 1237, "gap_to_leader": 66.796, "interval": 5.83}, {"date": "2024-06-09T18:22:05.592000+00:00", "session_key": 9531, "driver_number": 2, "meeting_key": 1237, "gap_to_leader": 66.747, "interval": 5.489}, {"date": "2024-06-09T18:22:11.365000+00:00", "session_key": 9531, "driver_number": 2, "meeting_key": 1237, "gap_to_leader": null, "interval": 5.405}, {"date": "2024-06-09T18:22:17.045000+00:00", "session_key": 9531, "interval": 5.192, "meeting_key": 1237, "gap_to_leader": 66.745, "driver_number": 2}, {"date": "2024-06-09T18:22:20.466000+00:00", "session_key": 9531, "interval": 5.096, "meeting_key": 1237, "gap_to_leader": 66.761, "driver_number": 2}, {"date": "2024-06-09T18:22:23.729000+00:00", "session_key": 9531, "interval": 5.09, "meeting_key": 1237, "gap_to_leader": 66.775, "driver_number": 2}, {"date": "2024-06-09T18:22:31.664000+00:00", "session_key": 9531, "interval": 5.064, "meeting_key": 1237, "gap_to_leader": 66.819, "driver_number": 2}, {"date": "2024-06-09T18:22:37.399000+00:00", "session_key": 9531, "interval": 5.296, "meeting_key": 1237, "gap_to_leader": 66.974, "driver_number": 2}, {"date": "2024-06-09T18:22:40.398000+00:00", "session_key": 9531, "interval": 5.298, "meeting_key": 1237, "gap_to_leader": 66.981, "driver_number": 2}, {"date": "2024-06-09T18:22:45.233000+00:00", "session_key": 9531, "interval": 5.257, "meeting_key": 1237, "gap_to_leader": 66.931, "driver_number": 2}, {"date": "2024-06-09T18:22:50.116000+00:00", "session_key": 9531, "interval": 5.078, "meeting_key": 1237, "gap_to_leader": 67.015, "driver_number": 2}, {"date": "2024-06-09T18:22:53.635000+00:00", "session_key": 9531, "interval": 4.875, "meeting_key": 1237, "gap_to_leader": 66.965, "driver_number": 2}, {"date": "2024-06-09T18:22:58.932000+00:00", "session_key": 9531, "interval": 2.168, "meeting_key": 1237, "gap_to_leader": 66.939, "driver_number": 2}, {"date": "2024-06-09T18:23:02.420000+00:00", "session_key": 9531, "interval": null, "meeting_key": 1237, "gap_to_leader": 67.01, "driver_number": 2}, {"date": "2024-06-09T18:23:14.078000+00:00", "session_key": 9531, "interval": 0.927, "meeting_key": 1237, "gap_to_leader": 67.993, "driver_number": 2}, {"date": "2024-06-09T18:23:18.062000+00:00", "session_key": 9531, "interval": 1.192, "meeting_key": 1237, "gap_to_leader": 68.639, "driver_number": 2}, {"date": "2024-06-09T18:23:22.762000+00:00", "session_key": 9531, "interval": 1.07, "meeting_key": 1237, "gap_to_leader": 68.837, "driver_number": 2}, {"date": "2024-06-09T18:23:26.425000+00:00", "session_key": 9531, "interval": 0.87, "meeting_key": 1237, "gap_to_leader": 69.101, "driver_number": 2}, {"date": "2024-06-09T18:23:32.935000+00:00", "session_key": 9531, "interval": 0.806, "meeting_key": 1237, "gap_to_leader": 69.43299999999999, "driver_number": 2}, {"date": "2024-06-09T18:23:37.590000+00:00", "session_key": 9531, "interval": 0.509, "meeting_key": 1237, "gap_to_leader": 69.819, "driver_number": 2}, {"date": "2024-06-09T18:23:43.446000+00:00", "session_key": 9531, "interval": 0.316, "meeting_key": 1237, "gap_to_leader": 69.945, "driver_number": 2}, {"date": "2024-06-09T18:23:49.489000+00:00", "session_key": 9531, "interval": 0.534, "meeting_key": 1237, "gap_to_leader": 70.338, "driver_number": 2}, {"date": "2024-06-09T18:23:52.877000+00:00", "session_key": 9531, "interval": 0.436, "meeting_key": 1237, "gap_to_leader": 70.37, "driver_number": 2}, {"date": "2024-06-09T18:23:56.198000+00:00", "session_key": 9531, "interval": 0.38, "meeting_key": 1237, "gap_to_leader": 70.373, "driver_number": 2}, {"date": "2024-06-09T18:24:04.309000+00:00", "session_key": 9531, "interval": 0.485, "meeting_key": 1237, "gap_to_leader": 70.754, "driver_number": 2}, {"date": "2024-06-09T18:24:09.958000+00:00", "session_key": 9531, "interval": 0.519, "meeting_key": 1237, "gap_to_leader": 70.926, "driver_number": 2}, {"date": "2024-06-09T18:24:12.933000+00:00", "session_key": 9531, "interval": 0.448, "meeting_key": 1237, "gap_to_leader": 70.897, "driver_number": 2}, {"date": "2024-06-09T18:24:17.702000+00:00", "session_key": 9531, "interval": 0.256, "meeting_key": 1237, "gap_to_leader": 70.73, "driver_number": 2}, {"date": "2024-06-09T18:24:22.868000+00:00", "session_key": 9531, "interval": 0.811, "meeting_key": 1237, "gap_to_leader": 71.19, "driver_number": 2}, {"date": "2024-06-09T18:24:26.424000+00:00", "session_key": 9531, "interval": 0.813, "meeting_key": 1237, "gap_to_leader": 71.206, "driver_number": 2}, {"date": "2024-06-09T18:24:31.685000+00:00", "session_key": 9531, "interval": 0.715, "meeting_key": 1237, "gap_to_leader": 71.175, "driver_number": 2}, {"date": "2024-06-09T18:24:35.585000+00:00", "session_key": 9531, "interval": 1.105, "meeting_key": 1237, "gap_to_leader": 71.56, "driver_number": 2}, {"date": "2024-06-09T18:24:41.652000+00:00", "session_key": 9531, "interval": 1.253, "meeting_key": 1237, "gap_to_leader": 71.761, "driver_number": 2}, {"date": "2024-06-09T18:24:46.442000+00:00", "session_key": 9531, "interval": 0.981, "meeting_key": 1237, "gap_to_leader": 71.67099999999999, "driver_number": 2}, {"date": "2024-06-09T18:24:49.963000+00:00", "session_key": 9531, "interval": 1.099, "meeting_key": 1237, "gap_to_leader": 71.775, "driver_number": 2}, {"date": "2024-06-09T18:24:54.357000+00:00", "session_key": 9531, "interval": 1.104, "meeting_key": 1237, "gap_to_leader": 71.64, "driver_number": 2}, {"date": "2024-06-09T18:24:57.858000+00:00", "session_key": 9531, "interval": 0.985, "meeting_key": 1237, "gap_to_leader": 71.676, "driver_number": 2}, {"date": "2024-06-09T18:25:04.208000+00:00", "session_key": 9531, "interval": 1.006, "meeting_key": 1237, "gap_to_leader": 71.581, "driver_number": 2}, {"date": "2024-06-09T18:25:08.504000+00:00", "session_key": 9531, "interval": 1.039, "meeting_key": 1237, "gap_to_leader": 71.82, "driver_number": 2}, {"date": "2024-06-09T18:25:14.313000+00:00", "session_key": 9531, "interval": 1.022, "meeting_key": 1237, "gap_to_leader": 71.893, "driver_number": 2}, {"date": "2024-06-09T18:25:19.954000+00:00", "session_key": 9531, "interval": 1.293, "meeting_key": 1237, "gap_to_leader": 71.976, "driver_number": 2}, {"date": "2024-06-09T18:25:23.303000+00:00", "session_key": 9531, "interval": 1.341, "meeting_key": 1237, "gap_to_leader": 71.993, "driver_number": 2}, {"date": "2024-06-09T18:25:26.616000+00:00", "session_key": 9531, "interval": 1.347, "meeting_key": 1237, "gap_to_leader": 72.03, "driver_number": 2}, {"date": "2024-06-09T18:25:34.401000+00:00", "session_key": 9531, "interval": 1.501, "meeting_key": 1237, "gap_to_leader": 72.113, "driver_number": 2}, {"date": "2024-06-09T18:25:39.937000+00:00", "session_key": 9531, "interval": 1.393, "meeting_key": 1237, "gap_to_leader": 72.194, "driver_number": 2}, {"date": "2024-06-09T18:25:42.989000+00:00", "session_key": 9531, "interval": 1.358, "meeting_key": 1237, "gap_to_leader": 72.2, "driver_number": 2}, {"date": "2024-06-09T18:25:47.873000+00:00", "session_key": 9531, "interval": 1.288, "meeting_key": 1237, "gap_to_leader": 72.147, "driver_number": 2}, {"date": "2024-06-09T18:25:52.836000+00:00", "session_key": 9531, "interval": 1.619, "meeting_key": 1237, "gap_to_leader": 72.417, "driver_number": 2}, {"date": "2024-06-09T18:25:56.404000+00:00", "session_key": 9531, "interval": 1.758, "meeting_key": 1237, "gap_to_leader": 72.337, "driver_number": 2}, {"date": "2024-06-09T18:26:01.643000+00:00", "session_key": 9531, "interval": 1.752, "meeting_key": 1237, "gap_to_leader": 72.346, "driver_number": 2}, {"date": "2024-06-09T18:26:05.465000+00:00", "session_key": 9531, "interval": 2.134, "meeting_key": 1237, "gap_to_leader": 72.738, "driver_number": 2}, {"date": "2024-06-09T18:26:11.253000+00:00", "session_key": 9531, "interval": 2.171, "meeting_key": 1237, "gap_to_leader": 72.684, "driver_number": 2}, {"date": "2024-06-09T18:26:16.075000+00:00", "session_key": 9531, "interval": 1.994, "meeting_key": 1237, "gap_to_leader": 72.34, "driver_number": 2}, {"date": "2024-06-09T18:26:19.457000+00:00", "session_key": 9531, "interval": 2.149, "meeting_key": 1237, "gap_to_leader": 72.303, "driver_number": 2}, {"date": "2024-06-09T18:26:23.745000+00:00", "session_key": 9531, "interval": 2.201, "meeting_key": 1237, "gap_to_leader": 72.027, "driver_number": 2}, {"date": "2024-06-09T18:26:27.165000+00:00", "session_key": 9531, "interval": 2.076, "meeting_key": 1237, "gap_to_leader": 72.007, "driver_number": 2}, {"date": "2024-06-09T18:26:33.300000+00:00", "session_key": 9531, "interval": 2.123, "meeting_key": 1237, "gap_to_leader": 72.017, "driver_number": 2}, {"date": "2024-06-09T18:26:37.751000+00:00", "session_key": 9531, "interval": 1.909, "meeting_key": 1237, "gap_to_leader": 72.168, "driver_number": 2}, {"date": "2024-06-09T18:26:43.577000+00:00", "session_key": 9531, "interval": 1.868, "meeting_key": 1237, "gap_to_leader": 72.202, "driver_number": 2}, {"date": "2024-06-09T18:26:49.260000+00:00", "session_key": 9531, "interval": 1.893, "meeting_key": 1237, "gap_to_leader": 72.356, "driver_number": 2}, {"date": "2024-06-09T18:26:52.579000+00:00", "session_key": 9531, "interval": 1.766, "meeting_key": 1237, "gap_to_leader": 72.363, "driver_number": 2}, {"date": "2024-06-09T18:26:55.868000+00:00", "session_key": 9531, "interval": 1.74, "meeting_key": 1237, "gap_to_leader": 72.379, "driver_number": 2}, {"date": "2024-06-09T18:27:03.582000+00:00", "session_key": 9531, "interval": 1.719, "meeting_key": 1237, "gap_to_leader": 72.493, "driver_number": 2}, {"date": "2024-06-09T18:27:09.345000+00:00", "session_key": 9531, "interval": 1.697, "meeting_key": 1237, "gap_to_leader": 72.722, "driver_number": 2}, {"date": "2024-06-09T18:27:12.418000+00:00", "session_key": 9531, "interval": 1.698, "meeting_key": 1237, "gap_to_leader": 72.754, "driver_number": 2}, {"date": "2024-06-09T18:27:17.255000+00:00", "session_key": 9531, "interval": 1.633, "meeting_key": 1237, "gap_to_leader": 72.715, "driver_number": 2}, {"date": "2024-06-09T18:27:22.097000+00:00", "session_key": 9531, "interval": 1.737, "meeting_key": 1237, "gap_to_leader": 72.849, "driver_number": 2}, {"date": "2024-06-09T18:27:25.595000+00:00", "session_key": 9531, "interval": 1.749, "meeting_key": 1237, "gap_to_leader": 72.798, "driver_number": 2}, {"date": "2024-06-09T18:27:30.797000+00:00", "session_key": 9531, "interval": 1.689, "meeting_key": 1237, "gap_to_leader": 72.822, "driver_number": 2}, {"date": "2024-06-09T18:27:34.804000+00:00", "session_key": 9531, "interval": 1.963, "meeting_key": 1237, "gap_to_leader": 73.229, "driver_number": 2}, {"date": "2024-06-09T18:27:40.582000+00:00", "session_key": 9531, "interval": 1.956, "meeting_key": 1237, "gap_to_leader": 73.488, "driver_number": 2}, {"date": "2024-06-09T18:27:45.404000+00:00", "session_key": 9531, "interval": 1.864, "meeting_key": 1237, "gap_to_leader": 73.30799999999999, "driver_number": 2}, {"date": "2024-06-09T18:27:48.837000+00:00", "session_key": 9531, "interval": 1.927, "meeting_key": 1237, "gap_to_leader": 73.465, "driver_number": 2}, {"date": "2024-06-09T18:27:53.229000+00:00", "session_key": 9531, "interval": 2.03, "meeting_key": 1237, "gap_to_leader": 73.492, "driver_number": 2}, {"date": "2024-06-09T18:27:56.815000+00:00", "session_key": 9531, "interval": 1.995, "meeting_key": 1237, "gap_to_leader": 73.685, "driver_number": 2}, {"date": "2024-06-09T18:28:03.118000+00:00", "session_key": 9531, "interval": 1.952, "meeting_key": 1237, "gap_to_leader": 74.002, "driver_number": 2}, {"date": "2024-06-09T18:28:07.930000+00:00", "session_key": 9531, "interval": 2.168, "meeting_key": 1237, "gap_to_leader": 74.367, "driver_number": 2}, {"date": "2024-06-09T18:28:13.706000+00:00", "session_key": 9531, "interval": 2.192, "meeting_key": 1237, "gap_to_leader": 74.491, "driver_number": 2}, {"date": "2024-06-09T18:28:19.249000+00:00", "session_key": 9531, "interval": 2.119, "meeting_key": 1237, "gap_to_leader": 74.551, "driver_number": 2}, {"date": "2024-06-09T18:28:22.508000+00:00", "session_key": 9531, "interval": 2.031, "meeting_key": 1237, "gap_to_leader": 74.583, "driver_number": 2}, {"date": "2024-06-09T18:28:25.728000+00:00", "session_key": 9531, "interval": 2.02, "meeting_key": 1237, "gap_to_leader": 74.612, "driver_number": 2}, {"date": "2024-06-09T18:28:33.521000+00:00", "session_key": 9531, "interval": 2.167, "meeting_key": 1237, "gap_to_leader": 74.907, "driver_number": 2}, {"date": "2024-06-09T18:28:39.054000+00:00", "session_key": 9531, "interval": 2.179, "meeting_key": 1237, "gap_to_leader": 74.914, "driver_number": 2}, {"date": "2024-06-09T18:28:42.144000+00:00", "session_key": 9531, "interval": 2.181, "meeting_key": 1237, "gap_to_leader": 74.934, "driver_number": 2}, {"date": "2024-06-09T18:28:46.987000+00:00", "session_key": 9531, "interval": 2.116, "meeting_key": 1237, "gap_to_leader": 74.847, "driver_number": 2}, {"date": "2024-06-09T18:28:51.716000+00:00", "session_key": 9531, "interval": 2.215, "meeting_key": 1237, "gap_to_leader": 74.908, "driver_number": 2}, {"date": "2024-06-09T18:28:55.070000+00:00", "session_key": 9531, "interval": 2.131, "meeting_key": 1237, "gap_to_leader": 74.82, "driver_number": 2}, {"date": "2024-06-09T18:29:00.283000+00:00", "session_key": 9531, "interval": 2.026, "meeting_key": 1237, "gap_to_leader": 74.809, "driver_number": 2}, {"date": "2024-06-09T18:29:03.983000+00:00", "session_key": 9531, "interval": 2.209, "meeting_key": 1237, "gap_to_leader": 75.083, "driver_number": 2}, {"date": "2024-06-09T18:29:09.680000+00:00", "session_key": 9531, "interval": 2.245, "meeting_key": 1237, "gap_to_leader": 75.178, "driver_number": 2}, {"date": "2024-06-09T18:29:14.649000+00:00", "session_key": 9531, "interval": 2.23, "meeting_key": 1237, "gap_to_leader": 74.95, "driver_number": 2}, {"date": "2024-06-09T18:29:17.990000+00:00", "session_key": 9531, "interval": 2.298, "meeting_key": 1237, "gap_to_leader": 74.968, "driver_number": 2}, {"date": "2024-06-09T18:29:22.245000+00:00", "session_key": 9531, "interval": 2.344, "meeting_key": 1237, "gap_to_leader": 74.774, "driver_number": 2}, {"date": "2024-06-09T18:29:25.713000+00:00", "session_key": 9531, "interval": 2.295, "meeting_key": 1237, "gap_to_leader": 74.869, "driver_number": 2}, {"date": "2024-06-09T18:29:31.812000+00:00", "session_key": 9531, "interval": 2.212, "meeting_key": 1237, "gap_to_leader": 74.977, "driver_number": 2}, {"date": "2024-06-09T18:29:36.150000+00:00", "session_key": 9531, "interval": 1.763, "meeting_key": 1237, "gap_to_leader": 75.011, "driver_number": 2}, {"date": "2024-06-09T18:29:41.870000+00:00", "session_key": 9531, "interval": 1.697, "meeting_key": 1237, "gap_to_leader": 75.001, "driver_number": 2}, {"date": "2024-06-09T18:29:47.305000+00:00", "session_key": 9531, "interval": 1.717, "meeting_key": 1237, "gap_to_leader": 75.05799999999999, "driver_number": 2}, {"date": "2024-06-09T18:29:50.529000+00:00", "session_key": 9531, "interval": 1.687, "meeting_key": 1237, "gap_to_leader": 75.006, "driver_number": 2}, {"date": "2024-06-09T18:29:53.771000+00:00", "session_key": 9531, "interval": 1.686, "meeting_key": 1237, "gap_to_leader": 75.02, "driver_number": 2}, {"date": "2024-06-09T18:30:01.290000+00:00", "session_key": 9531, "interval": 1.586, "meeting_key": 1237, "gap_to_leader": 75.002, "driver_number": 2}, {"date": "2024-06-09T18:30:06.822000+00:00", "session_key": 9531, "interval": 1.508, "meeting_key": 1237, "gap_to_leader": null, "driver_number": 2}, {"date": "2024-06-09T18:30:09.852000+00:00", "session_key": 9531, "interval": 1.481, "meeting_key": 1237, "gap_to_leader": 75.004, "driver_number": 2}, {"date": "2024-06-09T18:30:14.666000+00:00", "session_key": 9531, "interval": 1.417, "meeting_key": 1237, "gap_to_leader": 74.936, "driver_number": 2}, {"date": "2024-06-09T18:30:19.590000+00:00", "session_key": 9531, "interval": 1.61, "meeting_key": 1237, "gap_to_leader": 75.30199999999999, "driver_number": 2}, {"date": "2024-06-09T18:30:22.977000+00:00", "session_key": 9531, "interval": 1.55, "meeting_key": 1237, "gap_to_leader": 75.176, "driver_number": 2}, {"date": "2024-06-09T18:30:28.275000+00:00", "session_key": 9531, "interval": 1.472, "meeting_key": 1237, "gap_to_leader": 75.144, "driver_number": 2}, {"date": "2024-06-09T18:30:31.910000+00:00", "session_key": 9531, "interval": 1.744, "meeting_key": 1237, "gap_to_leader": 75.344, "driver_number": 2}, {"date": "2024-06-09T18:30:37.700000+00:00", "session_key": 9531, "interval": 1.422, "meeting_key": 1237, "gap_to_leader": 75.394, "driver_number": 2}, {"date": "2024-06-09T18:30:42.610000+00:00", "session_key": 9531, "driver_number": 2, "gap_to_leader": 75.45, "meeting_key": 1237, "interval": 1.513}, {"date": "2024-06-09T18:30:45.938000+00:00", "session_key": 9531, "driver_number": 2, "gap_to_leader": 75.498, "meeting_key": 1237, "interval": 1.58}, {"date": "2024-06-09T18:30:50.292000+00:00", "session_key": 9531, "driver_number": 2, "gap_to_leader": 75.46000000000001, "meeting_key": 1237, "interval": 1.741}, {"date": "2024-06-09T18:30:53.795000+00:00", "session_key": 9531, "driver_number": 2, "gap_to_leader": 75.513, "meeting_key": 1237, "interval": 1.744}, {"date": "2024-06-09T18:30:59.669000+00:00", "session_key": 9531, "driver_number": 2, "gap_to_leader": 75.494, "meeting_key": 1237, "interval": 1.746}, {"date": "2024-06-09T18:31:03.963000+00:00", "session_key": 9531, "driver_number": 2, "gap_to_leader": 75.44200000000001, "meeting_key": 1237, "interval": 1.607}, {"date": "2024-06-09T18:31:09.627000+00:00", "session_key": 9531, "driver_number": 2, "gap_to_leader": 75.437, "meeting_key": 1237, "interval": 1.606}, {"date": "2024-06-09T18:31:15.059000+00:00", "session_key": 9531, "interval": 1.597, "meeting_key": 1237, "gap_to_leader": 75.381, "driver_number": 2}, {"date": "2024-06-09T18:31:18.196000+00:00", "session_key": 9531, "interval": 1.576, "meeting_key": 1237, "gap_to_leader": 75.297, "driver_number": 2}, {"date": "2024-06-09T18:31:21.466000+00:00", "session_key": 9531, "interval": 1.564, "meeting_key": 1237, "gap_to_leader": 75.279, "driver_number": 2}, {"date": "2024-06-09T18:31:28.906000+00:00", "session_key": 9531, "interval": 1.577, "meeting_key": 1237, "gap_to_leader": 75.262, "driver_number": 2}, {"date": "2024-06-09T18:31:34.593000+00:00", "session_key": 9531, "interval": 1.695, "meeting_key": 1237, "gap_to_leader": 75.418, "driver_number": 2}, {"date": "2024-06-09T18:31:37.626000+00:00", "session_key": 9531, "interval": 1.688, "meeting_key": 1237, "gap_to_leader": 75.423, "driver_number": 2}, {"date": "2024-06-09T18:31:42.404000+00:00", "session_key": 9531, "driver_number": 2, "gap_to_leader": 75.336, "meeting_key": 1237, "interval": 1.615}, {"date": "2024-06-09T18:31:47.112000+00:00", "session_key": 9531, "driver_number": 2, "gap_to_leader": 75.354, "meeting_key": 1237, "interval": 1.722}, {"date": "2024-06-09T18:31:50.406000+00:00", "session_key": 9531, "driver_number": 2, "gap_to_leader": 75.22, "meeting_key": 1237, "interval": 1.63}, {"date": "2024-06-09T18:31:55.645000+00:00", "session_key": 9531, "driver_number": 2, "gap_to_leader": 75.207, "meeting_key": 1237, "interval": 1.55}, {"date": "2024-06-09T18:31:59.261000+00:00", "session_key": 9531, "interval": 1.633, "meeting_key": 1237, "gap_to_leader": 75.429, "driver_number": 2}, {"date": "2024-06-09T18:32:04.900000+00:00", "session_key": 9531, "interval": 1.586, "meeting_key": 1237, "gap_to_leader": 75.538, "driver_number": 2}, {"date": "2024-06-09T18:32:09.896000+00:00", "session_key": 9531, "interval": 1.686, "meeting_key": 1237, "gap_to_leader": 75.617, "driver_number": 2}, {"date": "2024-06-09T18:32:13.193000+00:00", "session_key": 9531, "interval": 1.682, "meeting_key": 1237, "gap_to_leader": 75.691, "driver_number": 2}, {"date": "2024-06-09T18:32:17.399000+00:00", "session_key": 9531, "interval": 1.64, "meeting_key": 1237, "gap_to_leader": 75.639, "driver_number": 2}, {"date": "2024-06-09T18:32:20.856000+00:00", "session_key": 9531, "interval": 1.528, "meeting_key": 1237, "gap_to_leader": 75.705, "driver_number": 2}, {"date": "2024-06-09T18:32:26.740000+00:00", "session_key": 9531, "interval": 1.49, "meeting_key": 1237, "gap_to_leader": 75.72, "driver_number": 2}, {"date": "2024-06-09T18:32:30.831000+00:00", "session_key": 9531, "interval": 1.422, "meeting_key": 1237, "gap_to_leader": null, "driver_number": 2}, {"date": "2024-06-09T18:32:36.514000+00:00", "session_key": 9531, "driver_number": 2, "gap_to_leader": 75.70400000000001, "meeting_key": 1237, "interval": 1.455}, {"date": "2024-06-09T18:32:41.838000+00:00", "session_key": 9531, "driver_number": 2, "gap_to_leader": 75.688, "meeting_key": 1237, "interval": 0.979}, {"date": "2024-06-09T18:32:45.092000+00:00", "session_key": 9531, "driver_number": 2, "gap_to_leader": 75.595, "meeting_key": 1237, "interval": 0.96}, {"date": "2024-06-09T18:32:48.266000+00:00", "session_key": 9531, "driver_number": 2, "gap_to_leader": 75.55199999999999, "meeting_key": 1237, "interval": 0.932}, {"date": "2024-06-09T18:32:55.814000+00:00", "session_key": 9531, "driver_number": 2, "gap_to_leader": 75.481, "meeting_key": 1237, "interval": 0.865}, {"date": "2024-06-09T18:33:01.290000+00:00", "session_key": 9531, "driver_number": 2, "gap_to_leader": 75.549, "meeting_key": 1237, "interval": 0.82}, {"date": "2024-06-09T18:33:04.265000+00:00", "session_key": 9531, "driver_number": 2, "gap_to_leader": 75.522, "meeting_key": 1237, "interval": 0.822}, {"date": "2024-06-09T18:33:08.866000+00:00", "session_key": 9531, "driver_number": 2, "gap_to_leader": 75.222, "meeting_key": 1237, "interval": 0.737}, {"date": "2024-06-09T18:33:13.655000+00:00", "session_key": 9531, "driver_number": 2, "gap_to_leader": 75.429, "meeting_key": 1237, "interval": 0.706}, {"date": "2024-06-09T18:33:16.974000+00:00", "session_key": 9531, "driver_number": 2, "gap_to_leader": 75.324, "meeting_key": 1237, "interval": 0.654}, {"date": "2024-06-09T18:33:22.122000+00:00", "session_key": 9531, "driver_number": 2, "gap_to_leader": 75.16499999999999, "meeting_key": 1237, "interval": 0.566}, {"date": "2024-06-09T18:33:25.905000+00:00", "session_key": 9531, "driver_number": 2, "gap_to_leader": 75.426, "meeting_key": 1237, "interval": 0.849}, {"date": "2024-06-09T18:33:31.905000+00:00", "session_key": 9531, "driver_number": 2, "gap_to_leader": 75.973, "meeting_key": 1237, "interval": 0.96}, {"date": "2024-06-09T18:33:36.985000+00:00", "session_key": 9531, "driver_number": 2, "gap_to_leader": 76.271, "meeting_key": 1237, "interval": 1.086}, {"date": "2024-06-09T18:33:40.609000+00:00", "session_key": 9531, "driver_number": 2, "gap_to_leader": 76.65299999999999, "meeting_key": 1237, "interval": 0.89}, {"date": "2024-06-09T18:33:44.870000+00:00", "session_key": 9531, "driver_number": 2, "gap_to_leader": 76.707, "meeting_key": 1237, "interval": 0.787}, {"date": "2024-06-09T18:33:48.375000+00:00", "session_key": 9531, "interval": 0.86, "meeting_key": 1237, "gap_to_leader": 76.88, "driver_number": 2}, {"date": "2024-06-09T18:33:54.304000+00:00", "session_key": 9531, "interval": 0.759, "meeting_key": 1237, "gap_to_leader": 76.996, "driver_number": 2}, {"date": "2024-06-09T18:33:58.516000+00:00", "session_key": 9531, "interval": 0.649, "meeting_key": 1237, "gap_to_leader": 77.05, "driver_number": 2}, {"date": "2024-06-09T18:34:04.168000+00:00", "session_key": 9531, "interval": 0.546, "meeting_key": 1237, "gap_to_leader": 76.997, "driver_number": 2}, {"date": "2024-06-09T18:34:09.882000+00:00", "session_key": 9531, "interval": 0.54, "meeting_key": 1237, "gap_to_leader": 77.354, "driver_number": 2}, {"date": "2024-06-09T18:34:13.930000+00:00", "session_key": 9531, "interval": 1.226, "meeting_key": 1237, "gap_to_leader": 78.105, "driver_number": 2}, {"date": "2024-06-09T18:34:17.231000+00:00", "session_key": 9531, "interval": 1.335, "meeting_key": 1237, "gap_to_leader": 78.221, "driver_number": 2}, {"date": "2024-06-09T18:34:24.806000+00:00", "session_key": 9531, "interval": 1.562, "meeting_key": 1237, "gap_to_leader": 78.39699999999999, "driver_number": 2}, {"date": "2024-06-09T18:34:30.268000+00:00", "session_key": 9531, "interval": 1.506, "meeting_key": 1237, "gap_to_leader": 78.383, "driver_number": 2}, {"date": "2024-06-09T18:34:33.273000+00:00", "session_key": 9531, "interval": 1.488, "meeting_key": 1237, "gap_to_leader": 78.367, "driver_number": 2}, {"date": "2024-06-09T18:34:38.092000+00:00", "session_key": 9531, "interval": 1.401, "meeting_key": 1237, "gap_to_leader": 78.301, "driver_number": 2}, {"date": "2024-06-09T18:34:42.907000+00:00", "session_key": 9531, "interval": 1.324, "meeting_key": 1237, "gap_to_leader": 78.625, "driver_number": 2}, {"date": "2024-06-09T18:34:46.168000+00:00", "session_key": 9531, "interval": 1.09, "meeting_key": 1237, "gap_to_leader": 78.463, "driver_number": 2}, {"date": "2024-06-09T18:34:51.385000+00:00", "session_key": 9531, "interval": 1.055, "meeting_key": 1237, "gap_to_leader": 78.408, "driver_number": 2}, {"date": "2024-06-09T18:34:55.100000+00:00", "session_key": 9531, "interval": 0.965, "meeting_key": 1237, "gap_to_leader": 77.68299999999999, "driver_number": 2}, {"date": "2024-06-09T18:35:01.151000+00:00", "session_key": 9531, "driver_number": 2, "gap_to_leader": 78.001, "meeting_key": 1237, "interval": 1.02}, {"date": "2024-06-09T18:35:05.943000+00:00", "session_key": 9531, "driver_number": 2, "gap_to_leader": 78.054, "meeting_key": 1237, "interval": 0.992}, {"date": "2024-06-09T18:35:09.254000+00:00", "session_key": 9531, "driver_number": 2, "gap_to_leader": 78.20400000000001, "meeting_key": 1237, "interval": 1.042}, {"date": "2024-06-09T18:35:13.471000+00:00", "session_key": 9531, "driver_number": 2, "gap_to_leader": 78.351, "meeting_key": 1237, "interval": 0.907}, {"date": "2024-06-09T18:35:16.844000+00:00", "session_key": 9531, "driver_number": 2, "gap_to_leader": 78.444, "meeting_key": 1237, "interval": 0.968}, {"date": "2024-06-09T18:35:22.979000+00:00", "session_key": 9531, "driver_number": 2, "gap_to_leader": 78.791, "meeting_key": 1237, "interval": 1.197}, {"date": "2024-06-09T18:35:27.528000+00:00", "session_key": 9531, "driver_number": 2, "gap_to_leader": 79.01, "meeting_key": 1237, "interval": 1.38}, {"date": "2024-06-09T18:35:33.134000+00:00", "session_key": 9531, "interval": 1.313, "meeting_key": 1237, "gap_to_leader": 79.04599999999999, "driver_number": 2}, {"date": "2024-06-09T18:35:39.710000+00:00", "session_key": 9531, "interval": 2.15, "meeting_key": 1237, "gap_to_leader": 80.179, "driver_number": 2}, {"date": "2024-06-09T18:35:43.510000+00:00", "session_key": 9531, "interval": 2.677, "meeting_key": 1237, "gap_to_leader": 80.838, "driver_number": 2}, {"date": "2024-06-09T18:35:46.797000+00:00", "session_key": 9531, "interval": 2.755, "meeting_key": 1237, "gap_to_leader": 80.953, "driver_number": 2}, {"date": "2024-06-09T18:35:54.238000+00:00", "session_key": 9531, "interval": 2.683, "meeting_key": 1237, "gap_to_leader": 80.816, "driver_number": 2}, {"date": "2024-06-09T18:35:59.753000+00:00", "session_key": 9531, "interval": 2.794, "meeting_key": 1237, "gap_to_leader": 80.845, "driver_number": 2}, {"date": "2024-06-09T18:36:02.768000+00:00", "session_key": 9531, "interval": 2.798, "meeting_key": 1237, "gap_to_leader": 80.89699999999999, "driver_number": 2}, {"date": "2024-06-09T18:36:07.584000+00:00", "session_key": 9531, "interval": 2.737, "meeting_key": 1237, "gap_to_leader": 81.08500000000001, "driver_number": 2}, {"date": "2024-06-09T18:36:12.231000+00:00", "session_key": 9531, "interval": 2.58, "meeting_key": 1237, "gap_to_leader": 81.675, "driver_number": 2}, {"date": "2024-06-09T18:36:15.485000+00:00", "session_key": 9531, "interval": 2.41, "meeting_key": 1237, "gap_to_leader": 81.56700000000001, "driver_number": 2}, {"date": "2024-06-09T18:36:20.663000+00:00", "session_key": 9531, "interval": 2.327, "meeting_key": 1237, "gap_to_leader": 81.498, "driver_number": 2}, {"date": "2024-06-09T18:36:24.161000+00:00", "session_key": 9531, "interval": 2.174, "meeting_key": 1237, "gap_to_leader": 81.709, "driver_number": 2}, {"date": "2024-06-09T18:36:30.140000+00:00", "session_key": 9531, "interval": 2.204, "meeting_key": 1237, "gap_to_leader": 81.937, "driver_number": 2}, {"date": "2024-06-09T18:36:34.906000+00:00", "session_key": 9531, "interval": 2.033, "meeting_key": 1237, "gap_to_leader": 81.885, "driver_number": 2}, {"date": "2024-06-09T18:36:38.259000+00:00", "session_key": 9531, "interval": 2.047, "meeting_key": 1237, "gap_to_leader": 82.15299999999999, "driver_number": 2}, {"date": "2024-06-09T18:36:42.443000+00:00", "session_key": 9531, "interval": 1.913, "meeting_key": 1237, "gap_to_leader": 82.363, "driver_number": 2}, {"date": "2024-06-09T18:36:45.880000+00:00", "session_key": 9531, "interval": 1.964, "meeting_key": 1237, "gap_to_leader": 82.452, "driver_number": 2}, {"date": "2024-06-09T18:36:51.765000+00:00", "session_key": 9531, "interval": 2.091, "meeting_key": 1237, "gap_to_leader": 82.862, "driver_number": 2}, {"date": "2024-06-09T18:36:56.067000+00:00", "session_key": 9531, "interval": 1.904, "meeting_key": 1237, "gap_to_leader": 82.98, "driver_number": 2}, {"date": "2024-06-09T18:37:01.798000+00:00", "session_key": 9531, "interval": 1.807, "meeting_key": 1237, "gap_to_leader": 83.03399999999999, "driver_number": 2}, {"date": "2024-06-09T18:37:07.167000+00:00", "session_key": 9531, "interval": 1.63, "meeting_key": 1237, "gap_to_leader": 83.31700000000001, "driver_number": 2}, {"date": "2024-06-09T18:37:10.389000+00:00", "session_key": 9531, "interval": 1.549, "meeting_key": 1237, "gap_to_leader": 83.293, "driver_number": 2}, {"date": "2024-06-09T18:37:13.577000+00:00", "session_key": 9531, "driver_number": 2, "gap_to_leader": 83.309, "meeting_key": 1237, "interval": 1.543}, {"date": "2024-06-09T18:37:20.980000+00:00", "session_key": 9531, "driver_number": 2, "gap_to_leader": 83.44, "meeting_key": 1237, "interval": 1.375}, {"date": "2024-06-09T18:37:26.528000+00:00", "session_key": 9531, "driver_number": 2, "gap_to_leader": 83.482, "meeting_key": 1237, "interval": 1.457}, {"date": "2024-06-09T18:37:29.561000+00:00", "session_key": 9531, "driver_number": 2, "gap_to_leader": 83.462, "meeting_key": 1237, "interval": 1.441}, {"date": "2024-06-09T18:37:34.366000+00:00", "session_key": 9531, "driver_number": 2, "gap_to_leader": 83.416, "meeting_key": 1237, "interval": 1.345}, {"date": "2024-06-09T18:37:39.084000+00:00", "session_key": 9531, "interval": 1.289, "meeting_key": 1237, "gap_to_leader": 83.80199999999999, "driver_number": 2}, {"date": "2024-06-09T18:37:42.228000+00:00", "session_key": 9531, "interval": 1.083, "meeting_key": 1237, "gap_to_leader": 83.82300000000001, "driver_number": 2}, {"date": "2024-06-09T18:37:47.418000+00:00", "session_key": 9531, "interval": 1.03, "meeting_key": 1237, "gap_to_leader": 83.8, "driver_number": 2}, {"date": "2024-06-09T18:37:51.092000+00:00", "session_key": 9531, "interval": 0.966, "meeting_key": 1237, "gap_to_leader": 84.06700000000001, "driver_number": 2}, {"date": "2024-06-09T18:37:56.927000+00:00", "session_key": 9531, "interval": 1.011, "meeting_key": 1237, "gap_to_leader": 84.324, "driver_number": 2}, {"date": "2024-06-09T18:38:02.333000+00:00", "session_key": 9531, "interval": 1.696, "meeting_key": 1237, "gap_to_leader": 84.952, "driver_number": 2}, {"date": "2024-06-09T18:38:06.512000+00:00", "session_key": 9531, "interval": 2.511, "meeting_key": 1237, "gap_to_leader": "+1 LAP", "driver_number": 2}, {"date": "2024-06-09T18:38:11.233000+00:00", "session_key": 9531, "interval": 2.897, "meeting_key": 1237, "gap_to_leader": "+1 LAP", "driver_number": 2}, {"date": "2024-06-09T18:38:14.785000+00:00", "session_key": 9531, "interval": 2.984, "meeting_key": 1237, "gap_to_leader": "+1 LAP", "driver_number": 2}, {"date": "2024-06-09T18:38:20.617000+00:00", "session_key": 9531, "interval": 3.028, "meeting_key": 1237, "gap_to_leader": "+1 LAP", "driver_number": 2}, {"date": "2024-06-09T18:38:24.909000+00:00", "session_key": 9531, "interval": 2.914, "meeting_key": 1237, "gap_to_leader": "+1 LAP", "driver_number": 2}, {"date": "2024-06-09T18:38:30.621000+00:00", "session_key": 9531, "interval": 2.913, "meeting_key": 1237, "gap_to_leader": "+1 LAP", "driver_number": 2}, {"date": "2024-06-09T18:38:36.019000+00:00", "session_key": 9531, "interval": 2.816, "meeting_key": 1237, "gap_to_leader": "+1 LAP", "driver_number": 2}, {"date": "2024-06-09T18:38:39.312000+00:00", "session_key": 9531, "interval": 2.624, "meeting_key": 1237, "gap_to_leader": "+1 LAP", "driver_number": 2}, {"date": "2024-06-09T18:38:42.594000+00:00", "session_key": 9531, "interval": 2.213, "meeting_key": 1237, "gap_to_leader": "+1 LAP", "driver_number": 2}, {"date": "2024-06-09T18:38:49.983000+00:00", "session_key": 9531, "interval": 1.237, "meeting_key": 1237, "gap_to_leader": "+1 LAP", "driver_number": 2}, {"date": "2024-06-09T18:38:55.537000+00:00", "session_key": 9531, "interval": 1.415, "meeting_key": 1237, "gap_to_leader": "+1 LAP", "driver_number": 2}, {"date": "2024-06-09T18:38:58.545000+00:00", "session_key": 9531, "interval": 1.428, "meeting_key": 1237, "gap_to_leader": "+1 LAP", "driver_number": 2}, {"date": "2024-06-09T18:39:03.327000+00:00", "session_key": 9531, "interval": 1.36, "meeting_key": 1237, "gap_to_leader": "+1 LAP", "driver_number": 2}, {"date": "2024-06-09T18:39:07.898000+00:00", "session_key": 9531, "interval": 1.159, "meeting_key": 1237, "gap_to_leader": "+1 LAP", "driver_number": 2}, {"date": "2024-06-09T18:39:11.233000+00:00", "session_key": 9531, "interval": 0.955, "meeting_key": 1237, "gap_to_leader": "+1 LAP", "driver_number": 2}, {"date": "2024-06-09T18:39:16.373000+00:00", "session_key": 9531, "interval": 0.913, "meeting_key": 1237, "gap_to_leader": "+1 LAP", "driver_number": 2}, {"date": "2024-06-09T18:39:19.971000+00:00", "session_key": 9531, "interval": 0.879, "meeting_key": 1237, "gap_to_leader": "+1 LAP", "driver_number": 2}, {"date": "2024-06-09T18:39:25.924000+00:00", "session_key": 9531, "interval": 0.905, "meeting_key": 1237, "gap_to_leader": "+1 LAP", "driver_number": 2}, {"date": "2024-06-09T18:39:30.577000+00:00", "session_key": 9531, "interval": 0.751, "meeting_key": 1237, "gap_to_leader": "+1 LAP", "driver_number": 2}, {"date": "2024-06-09T18:39:33.940000+00:00", "session_key": 9531, "interval": 0.719, "meeting_key": 1237, "gap_to_leader": "+1 LAP", "driver_number": 2}, {"date": "2024-06-09T18:39:40.471000+00:00", "session_key": 9531, "interval": 2.716, "meeting_key": 1237, "gap_to_leader": "+1 LAP", "driver_number": 2}]